reduction_operators.v
module reduction_operators();

    reg [4:0] my_val1 = 5'b1_1111;
    reg [8:0] my_val2 = 9'b1_0101_1110;
    reg result;

    initial begin
        $dumpfile("reduction_operators.vcd");
        $dumpvars(0, reduction_operators);
        $monitor("MON my_val1=%b, my_val2=%b, result=%b", my_val1, my_val2, result);
    end

    initial begin
        result = &my_val1; // AND reduction
        #1;
        result = &my_val2;

        #1;
        result = ~my_val2; // NOT reduction

        #1;
        result = ~&my_val1; // NAND reduction

        #1;
        result = |my_val2; // OR reduction

        #1;
        result = ~|my_val2; // NOR reduction

        #1;
        result = ^my_val1; // XOR reduction

        #1;
        result = ~^my_val1; // XNOR reduction
    end
endmodule

reduction_operators.vcd
$date
	Sat Feb  7 11:44:29 2026
$end
$version
	Icarus Verilog
$end
$timescale
	1s
$end
$scope module reduction_operators $end
$var reg 5 ! my_val1 [4:0] $end
$var reg 9 " my_val2 [8:0] $end
$var reg 1 # result $end
$upscope $end
$enddefinitions $end
$comment Show the parameter values. $end
$dumpall
$end
#0
$dumpvars
1#
b101011110 "
b11111 !
$end
#1
0#
#2
1#
#3
0#
#4
1#
#5
0#
#6
1#
#7
0#
