bitwise_opperators.v

`timescale 1ns/100ps

module bitwise_operators(
    // no inputs here
    );

    reg [5:0] x = 0;
    reg [5:0] y = 0;
    reg [5:0] result = 0;


    initial begin 
        $dumpfile("wave.vcd");
        $dumpvars(0, bitwise_operators);
        $monitor("MON x=%b, y=%b, results=%b", x, y, result);
    end

    initial begin
        #1;
        x = 6'b00_0101;
        y = 6'b11_0001;
        result = x & y; // AND

        #1;
        result = ~(x & y);

        #1;
        x = 6'b10_0101;
        y = 6'b01_1011;
        result = x | y; // OR

        #1
        result = ~(x | y);

        #1
        x = 6'b01_0110;
        y = 6'b01_1011;
        result = x ^ y; // XOR

        #1
        result = x ~^ y;  // NXOR

        #1
        x = y;
        result = ~(x ^ y);
    end
endmodule

wave.vcd
$date
	Sat Feb  7 10:32:40 2026
$end
$version
	Icarus Verilog
$end
$timescale
	100ps
$end
$scope module bitwise_operators $end
$var reg 6 ! result [5:0] $end
$var reg 6 " x [5:0] $end
$var reg 6 # y [5:0] $end
$upscope $end
$enddefinitions $end
$comment Show the parameter values. $end
$dumpall
$end
#0
$dumpvars
b0 #
b0 "
b0 !
$end
#10
b1 !
b110001 #
b101 "
#20
b111110 !
#30
b111111 !
b11011 #
b100101 "
#40
b0 !
#50
b1101 !
b10110 "
#60
b110010 !
#70
b111111 !
b11011 "
