ENPM_818G_HW/light_controller.v
module light_controller(

    // The set state of the light currently
    // 0 = red
    // 3 = green
    // 1 = yellow
    output reg [1:0] set_light_color,

    // Clock input
    // Clk
    input clk,

    // Car has arrived
    input car_has_arrived,

    // The state of the light currently
    // 0 = red
    // 3 = green
    // 1 = yellow
    input [1:0] current_light_state,
    
    // Street Light State
    // 1 can allow green
    // 0 can't allow green
    input street_light_controller);

    reg [3:0] yield_time = 0;
    reg [8:0] go_time = 0;


    // keep track GREEN
    // Transitioning to YIELD
    always @(posedge clk or posedge car_has_arrived) begin
        if(!street_light_controller) begin
            if (current_light_state == 2'b11) begin 
                if (car_has_arrived) begin // TODO: implement the clock
                    assign set_light_color = 2'b01; // Setting light to YIELD
                end
            end
        end
    end

    // Keeping track of YIELD 
    // Transitioning it to GREEN
    always @(posedge clk) begin
        if (current_light_state == 2'b01) begin 
            if (yield_time < 4'd5) begin
                yield_time = yield_time + 1; // incrementing yield time
            end
            else if (yield_time >= 4'd5) begin
                assign set_light_color = 2'b00;    // setting the lights to RED
            end
        end
        else if (current_light_state == 2'b00) begin 
            if (street_light_controller) begin
                assign set_light_color = 2'b11; // Setting light to GREEN
            end
        end
    end

endmodule

ENPM_818G_HW/street_light_controller.v
module street_light_controller(
    output [1:0] street_light1,
    output [1:0] street_light2,
    output [1:0] street_light3,
    output [1:0] street_light4,
    input button_pushed,
    input clk,
    input reset);

    reg north_south_street_light_controller = 1'b0;
    reg east_west_street_light_controller = 1'b0;

    reg patch_switches = 1'b0;

    reg [1:0] current_light_state1;
    reg [1:0] current_light_state2;
    reg [1:0] current_light_state3;
    reg [1:0] current_light_state4;

    reg [3:0] startuptime = 4'b0000;

    light_controller LIGHT1(
        .set_light_color(street_light1),
        .clk(clk),
        .car_has_arrived(button_pushed),
        .current_light_state(current_light_state1),
        .street_light_controller(north_south_street_light_controller)
    );

    light_controller LIGHT3(
        .set_light_color(street_light3),
        .clk(clk),
        .car_has_arrived(button_pushed),
        .current_light_state(current_light_state3),
        .street_light_controller(north_south_street_light_controller)
    );

    light_controller LIGHT2(
        .set_light_color(street_light2),
        .clk(clk),
        .car_has_arrived(button_pushed),
        .current_light_state(current_light_state2),
        .street_light_controller(east_west_street_light_controller)
    );

    light_controller LIGHT4(
        .set_light_color(street_light4),
        .clk(clk),
        .car_has_arrived(button_pushed),
        .current_light_state(current_light_state4),
        .street_light_controller(east_west_street_light_controller)
    );

    always @(*) begin
        $monitor("Street_light 1 = %2b, Street_light 3 = %2b, 1&3_con = %b, Street_light 2 = %2b, Street_light 4 = %2b, 2&4_con = %b, push button = %d, reset = %d",
                 street_light1,
                 street_light3,
                 north_south_street_light_controller,
                 street_light2,
                 street_light4,
                 east_west_street_light_controller,
                 button_pushed,
                 reset);
    end

    always @(posedge reset) begin
        current_light_state1 = 2'b00;
        current_light_state2 = 2'b11;
        current_light_state3 = 2'b00;
        current_light_state4 = 2'b11;
        patch_switches = 1'b1;

        north_south_street_light_controller = patch_switches;
        east_west_street_light_controller = !patch_switches;
    end

    always @(posedge button_pushed) begin
        // flip the bits for the street light controllers once the corresponding lights are set
        if (((street_light1 & street_light3) ^ 
             (street_light2 & street_light4)) == 2'b11) begin
            // Light 2 & 4
            east_west_street_light_controller = patch_switches;
            // Light 1 & 3
            north_south_street_light_controller = !patch_switches;

            // // Patch Switches
            patch_switches = !patch_switches;
        end
    end

    always @(posedge clk) begin
        current_light_state1 = street_light1;
        current_light_state2 = street_light2;
        current_light_state3 = street_light3;
        current_light_state4 = street_light4;
    end

endmodule

ENPM_818G_HW/HW1/street_light_controller_tb.v
`timescale 1ns/1ps
module street_light_controller_tb();

    wire [1:0] street_light1;
    wire [1:0] street_light2;
    wire [1:0] street_light3;
    wire [1:0] street_light4;
    reg button_pushed=0;
    reg clk=0;
    reg reset=0;

    street_light_controller CONTROL1
    (
        .street_light1(street_light1),
        .street_light2(street_light2),
        .street_light3(street_light3),
        .street_light4(street_light4),
        .button_pushed(button_pushed),
        .clk(clk),
        .reset(reset)
    );

    // initial begin
    //     $dumpfile("street_light_controller.vcd");
    //     $dumpvars(0, street_light_controller_tb);
    //     $monitor("Street_light 1 = %2b, Street_light 3 = %2b, Street_light 2 = %2b, Street_light 4 = %2b, push button = %d",
    //              street_light1,
    //              street_light3,
    //              street_light2,
    //              street_light4,
    //              button_pushed);
    // end

    initial begin
        forever #1 clk = !clk;
    end;

    initial begin

        #1;
        reset = 1;
        #1;
        reset = 0;

        #10;
        button_pushed = 0;

        #10;
        button_pushed = 1;
        #1;
        button_pushed = 0;

        #1;
        reset = 1;
        #1;
        reset = 0;

        #500;
        button_pushed = 1;
        #1;
        button_pushed = 0;

        #500;
        button_pushed = 1;
        #1;
        button_pushed = 0;

        #500;
        button_pushed = 1;
        #1;
        button_pushed = 0;


        #1000;
        button_pushed = 0;


        $finish();
    end

endmodule

ENPM_818G_HW/street_light_controller.vcd
$date
	Wed Feb 25 12:00:32 2026
$end
$version
	Icarus Verilog
$end
$timescale
	1ps
$end
$scope module street_light_controller_tb $end
$var wire 2 ! street_light4 [1:0] $end
$var wire 2 " street_light3 [1:0] $end
$var wire 2 # street_light2 [1:0] $end
$var wire 2 $ street_light1 [1:0] $end
$var reg 1 % button_pushed $end
$var reg 1 & clk $end
$var reg 1 ' reset $end
$scope module CONTROL1 $end
$var wire 1 % button_pushed $end
$var wire 1 & clk $end
$var wire 1 ' reset $end
$var wire 2 ( street_light4 [1:0] $end
$var wire 2 ) street_light3 [1:0] $end
$var wire 2 * street_light2 [1:0] $end
$var wire 2 + street_light1 [1:0] $end
$var reg 2 , current_light_state1 [1:0] $end
$var reg 2 - current_light_state2 [1:0] $end
$var reg 2 . current_light_state3 [1:0] $end
$var reg 2 / current_light_state4 [1:0] $end
$var reg 1 0 east_west_street_light_controller $end
$var reg 1 1 north_south_street_light_controller $end
$var reg 1 2 patch_switches $end
$var reg 4 3 startuptime [3:0] $end
$scope module LIGHT1 $end
$var wire 1 % car_has_arrived $end
$var wire 1 & clk $end
$var wire 2 4 current_light_state [1:0] $end
$var wire 1 1 street_light_controller $end
$var reg 9 5 go_time [8:0] $end
$var reg 2 6 set_light_color [1:0] $end
$var reg 4 7 yield_time [3:0] $end
$upscope $end
$scope module LIGHT2 $end
$var wire 1 % car_has_arrived $end
$var wire 1 & clk $end
$var wire 2 8 current_light_state [1:0] $end
$var wire 1 0 street_light_controller $end
$var reg 9 9 go_time [8:0] $end
$var reg 2 : set_light_color [1:0] $end
$var reg 4 ; yield_time [3:0] $end
$upscope $end
$scope module LIGHT3 $end
$var wire 1 % car_has_arrived $end
$var wire 1 & clk $end
$var wire 2 < current_light_state [1:0] $end
$var wire 1 1 street_light_controller $end
$var reg 9 = go_time [8:0] $end
$var reg 2 > set_light_color [1:0] $end
$var reg 4 ? yield_time [3:0] $end
$upscope $end
$scope module LIGHT4 $end
$var wire 1 % car_has_arrived $end
$var wire 1 & clk $end
$var wire 2 @ current_light_state [1:0] $end
$var wire 1 0 street_light_controller $end
$var reg 9 A go_time [8:0] $end
$var reg 2 B set_light_color [1:0] $end
$var reg 4 C yield_time [3:0] $end
$upscope $end
$upscope $end
$upscope $end
$enddefinitions $end
$comment Show the parameter values. $end
$dumpall
$end
#0
$dumpvars
b0 C
bx B
b0 A
bx @
b0 ?
bx >
b0 =
bx <
b0 ;
bx :
b0 9
bx 8
b0 7
bx 6
b0 5
bx 4
b0 3
02
01
00
bx /
bx .
bx -
bx ,
bx +
bx *
bx )
bx (
0'
0&
0%
bx $
bx #
bx "
bx !
$end
#1000
11
12
b11 !
b11 (
b11 B
b11 /
b11 @
b0 "
b0 )
b0 >
b0 .
b0 <
b11 #
b11 *
b11 :
b11 -
b11 8
b0 $
b0 +
b0 6
b0 ,
b0 4
1'
1&
#2000
0'
0&
#3000
b1 !
b1 (
b1 B
b1 #
b1 *
b1 :
b11 "
b11 )
b11 >
b11 $
b11 +
b11 6
1&
#4000
0&
#5000
1&
#6000
0&
#7000
1&
#8000
0&
#9000
1&
#10000
0&
#11000
1&
#12000
0&
#13000
1&
#14000
0&
#15000
1&
#16000
0&
#17000
1&
#18000
0&
#19000
1&
#20000
0&
#21000
1&
#22000
0&
1%
#23000
1&
0%
#24000
0&
1'
#25000
1&
0'
